{
  "id": "11-subcontract-rename",
  "title": "Subcontract field renamed: `wholesaleCostCents` no longer present; `costCents` is the actual key",
  "hypothesis": "The current public schema documents Subcontract.costCents as the wholesale/base-cost field. Older integrations referencing `wholesaleCostCents` get undefined. This test scans live subcontracts and reports which keys are actually present.",
  "verdict": "CONFIRMED_BUG",
  "summary": "Scanned 5 subcontracts across 400 orders. costCents present on 5 (populated on 5). wholesaleCostCents present on 0 (populated on 0). retailCostCents populated on 5.",
  "evidence": {
    "endpoint": "GET /v3/order/:id/service",
    "ordersScanned": 400,
    "subcontractsObserved": 5,
    "keysObserved": [
      "category",
      "categoryId",
      "companyId",
      "costCents",
      "createdDate",
      "discountCents",
      "discountPercent",
      "discountValueType",
      "id",
      "labels",
      "locationId",
      "meta",
      "metadata",
      "name",
      "note",
      "orderId",
      "ordinal",
      "retailCostCents",
      "serviceId",
      "showNote",
      "sourceItemId",
      "taxable",
      "taxableGST",
      "taxableHST",
      "taxablePST",
      "updatedDate",
      "vendor",
      "vendorId"
    ],
    "hasCostCents": 5,
    "hasWholesaleCostCents": 0,
    "costCentsPopulated": 5,
    "wholesaleCostCentsPopulated": 0,
    "retailCostCentsPopulated": 5
  },
  "requests": [
    {
      "method": "GET",
      "path": "/order",
      "query": {
        "limit": "100",
        "skip": "0"
      },
      "status": 200,
      "durationMs": 231,
      "responseSummary": {
        "dataLength": 100,
        "metaTotal": 5720,
        "metaHasMore": true
      }
    },
    {
      "method": "GET",
      "path": "/order",
      "query": {
        "limit": "100",
        "skip": "100"
      },
      "status": 200,
      "durationMs": 256,
      "responseSummary": {
        "dataLength": 100,
        "metaTotal": 5720,
        "metaHasMore": true
      }
    },
    {
      "method": "GET",
      "path": "/order",
      "query": {
        "limit": "100",
        "skip": "200"
      },
      "status": 200,
      "durationMs": 274,
      "responseSummary": {
        "dataLength": 100,
        "metaTotal": 5720,
        "metaHasMore": true
      }
    },
    {
      "method": "GET",
      "path": "/order",
      "query": {
        "limit": "100",
        "skip": "300"
      },
      "status": 200,
      "durationMs": 272,
      "responseSummary": {
        "dataLength": 100,
        "metaTotal": 5720,
        "metaHasMore": true
      }
    },
    {
      "method": "GET",
      "path": "/order/681e106d-093f-42e4-853c-9db283918cd8/service",
      "status": 200,
      "durationMs": 167,
      "responseSummary": {
        "dataLength": 1
      }
    },
    {
      "method": "GET",
      "path": "/order/67fec9a5-a9b6-47f2-b2d9-148cd1efe00e/service",
      "status": 200,
      "durationMs": 170,
      "responseSummary": {
        "dataLength": 1
      }
    },
    {
      "method": "GET",
      "path": "/order/7165340b-c281-4859-9945-77420aca836d/service",
      "status": 200,
      "durationMs": 165,
      "responseSummary": {
        "dataLength": 2
      }
    },
    {
      "method": "GET",
      "path": "/order/71676835-cbb2-4b6c-9840-155cfbbdd8ce/service",
      "status": 200,
      "durationMs": 164,
      "responseSummary": {
        "dataLength": 2
      }
    },
    {
      "method": "GET",
      "path": "/order/716b53de-9665-427f-922a-18772b5d41c2/service",
      "status": 200,
      "durationMs": 189,
      "responseSummary": {
        "dataLength": 1
      }
    },
    {
      "method": "GET",
      "path": "/order/d0e0cb76-3abd-4ec0-a5f7-551986739b32/service",
      "status": 200,
      "durationMs": 188,
      "responseSummary": {
        "dataLength": 3
      }
    },
    {
      "method": "GET",
      "path": "/order/d0ecddeb-2ed0-4975-acb0-4df342e644c7/service",
      "status": 200,
      "durationMs": 170,
      "responseSummary": {
        "dataLength": 1
      }
    },
    {
      "method": "GET",
      "path": "/order/d0ecf8a7-d37b-4f25-ac49-d47277fdb913/service",
      "status": 200,
      "durationMs": 187,
      "responseSummary": {
        "dataLength": 3
      }
    },
    {
      "method": "GET",
      "path": "/order/d1052d1b-960d-4c9e-a5b8-8f8e00922771/service",
      "status": 200,
      "durationMs": 182,
      "responseSummary": {
        "dataLength": 2
      }
    },
    {
      "method": "GET",
      "path": "/order/d107a4ce-6113-434c-9725-7d653d1289ef/service",
      "status": 200,
      "durationMs": 164,
      "responseSummary": {
        "dataLength": 2
      }
    },
    {
      "method": "GET",
      "path": "/order/d10c7a54-22b9-4124-b30f-bd2cc919a50c/service",
      "status": 200,
      "durationMs": 211,
      "responseSummary": {
        "dataLength": 2
      }
    },
    {
      "method": "GET",
      "path": "/order/d110db7c-2de7-468f-b3f0-9486926e9cad/service",
      "status": 200,
      "durationMs": 197,
      "responseSummary": {
        "dataLength": 2
      }
    },
    {
      "method": "GET",
      "path": "/order/d12b3374-a995-45db-94da-255c6b13dbb4/service",
      "status": 200,
      "durationMs": 170,
      "responseSummary": {
        "dataLength": 0
      }
    },
    {
      "method": "GET",
      "path": "/order/d1359682-3fec-435d-b3e6-b5312131001d/service",
      "status": 200,
      "durationMs": 162,
      "responseSummary": {
        "dataLength": 2
      }
    },
    {
      "method": "GET",
      "path": "/order/d139b36d-5aed-4287-95ea-ac97add6df02/service",
      "status": 200,
      "durationMs": 181,
      "responseSummary": {
        "dataLength": 4
      }
    },
    {
      "method": "GET",
      "path": "/order/d151c26f-e163-4e97-b9f7-02723e32f3c4/service",
      "status": 200,
      "durationMs": 166,
      "responseSummary": {
        "dataLength": 1
      }
    },
    {
      "method": "GET",
      "path": "/order/d1636a10-d774-46d6-ac84-9b356d72a69d/service",
      "status": 200,
      "durationMs": 174,
      "responseSummary": {
        "dataLength": 2
      }
    },
    {
      "method": "GET",
      "path": "/order/d1686ed3-70f1-4302-bce3-6fb5951dc48a/service",
      "status": 200,
      "durationMs": 165,
      "responseSummary": {
        "dataLength": 2
      }
    },
    {
      "method": "GET",
      "path": "/order/d1790e8d-c7ea-4eca-9a03-f6377d40c22e/service",
      "status": 200,
      "durationMs": 181,
      "responseSummary": {
        "dataLength": 1
      }
    },
    {
      "method": "GET",
      "path": "/order/d19f658b-5603-4e7f-8de9-66aa42693c77/service",
      "status": 200,
      "durationMs": 179,
      "responseSummary": {
        "dataLength": 2
      }
    },
    {
      "method": "GET",
      "path": "/order/d1a50305-d8f5-4fdd-b9b5-856d601750dd/service",
      "status": 200,
      "durationMs": 171,
      "responseSummary": {
        "dataLength": 1
      }
    },
    {
      "method": "GET",
      "path": "/order/d1a57699-d3ef-4221-a713-5c37a27104fa/service",
      "status": 200,
      "durationMs": 156,
      "responseSummary": {
        "dataLength": 1
      }
    },
    {
      "method": "GET",
      "path": "/order/d1a68d9b-35bc-4736-bb08-f507dc411010/service",
      "status": 200,
      "durationMs": 172,
      "responseSummary": {
        "dataLength": 1
      }
    },
    {
      "method": "GET",
      "path": "/order/d1aa28f6-8959-45a0-8fab-1082841e93a8/service",
      "status": 200,
      "durationMs": 202,
      "responseSummary": {
        "dataLength": 1
      }
    },
    {
      "method": "GET",
      "path": "/order/d1b779d3-a637-4266-bdf2-6e60cf76e58b/service",
      "status": 200,
      "durationMs": 179,
      "responseSummary": {
        "dataLength": 0
      }
    },
    {
      "method": "GET",
      "path": "/order/d1d3bf58-dbd7-4a3f-92a8-b8d5ed7be6bf/service",
      "status": 200,
      "durationMs": 178,
      "responseSummary": {
        "dataLength": 0
      }
    },
    {
      "method": "GET",
      "path": "/order/d1e286d5-e6e2-4179-af8a-e17fc9ab44fa/service",
      "status": 200,
      "durationMs": 191,
      "responseSummary": {
        "dataLength": 2
      }
    },
    {
      "method": "GET",
      "path": "/order/d1e5b45c-e33f-4fd0-9077-820183d73fdf/service",
      "status": 200,
      "durationMs": 175,
      "responseSummary": {
        "dataLength": 2
      }
    },
    {
      "method": "GET",
      "path": "/order/d1ed0635-316a-4c81-a4f6-a2f332bd1983/service",
      "status": 200,
      "durationMs": 171,
      "responseSummary": {
        "dataLength": 4
      }
    },
    {
      "method": "GET",
      "path": "/order/d1f4352d-90cc-4fc5-a22f-edecf11510ec/service",
      "status": 200,
      "durationMs": 158,
      "responseSummary": {
        "dataLength": 0
      }
    },
    {
      "method": "GET",
      "path": "/order/d207a8ec-b4ad-41ef-a15a-080dbd322891/service",
      "status": 200,
      "durationMs": 179,
      "responseSummary": {
        "dataLength": 2
      }
    },
    {
      "method": "GET",
      "path": "/order/d20aa6f9-c61b-4520-9e8d-7e04fabb7ba0/service",
      "status": 200,
      "durationMs": 176,
      "responseSummary": {
        "dataLength": 1
      }
    },
    {
      "method": "GET",
      "path": "/order/d2190082-3701-4269-88fa-24ba250fed26/service",
      "status": 200,
      "durationMs": 171,
      "responseSummary": {
        "dataLength": 1
      }
    },
    {
      "method": "GET",
      "path": "/order/d21ef918-1ccd-43b7-b7f1-3ca30239143d/service",
      "status": 200,
      "durationMs": 164,
      "responseSummary": {
        "dataLength": 0
      }
    },
    {
      "method": "GET",
      "path": "/order/67cec320-9e35-48e7-9d95-122207d7fdce/service",
      "status": 200,
      "durationMs": 171,
      "responseSummary": {
        "dataLength": 0
      }
    },
    {
      "method": "GET",
      "path": "/order/67d1801e-e5ca-4db2-b6e2-a116c21136ac/service",
      "status": 200,
      "durationMs": 165,
      "responseSummary": {
        "dataLength": 1
      }
    },
    {
      "method": "GET",
      "path": "/order/67acf823-d380-4081-b3f0-4c85d7ef77d4/service",
      "status": 200,
      "durationMs": 182,
      "responseSummary": {
        "dataLength": 2
      }
    },
    {
      "method": "GET",
      "path": "/order/67b4e1d4-ea46-4720-bdd1-42013c72cca2/service",
      "status": 200,
      "durationMs": 182,
      "responseSummary": {
        "dataLength": 1
      }
    },
    {
      "method": "GET",
      "path": "/order/66cec727-3a02-469f-b875-b07c276bfde1/service",
      "status": 200,
      "durationMs": 177,
      "responseSummary": {
        "dataLength": 1
      }
    },
    {
      "method": "GET",
      "path": "/order/66622846-120c-48ce-a0e7-46256f9084f9/service",
      "status": 200,
      "durationMs": 163,
      "responseSummary": {
        "dataLength": 2
      }
    },
    {
      "method": "GET",
      "path": "/order/62425461-0a6b-4933-908f-4f6d25e47c3d/service",
      "status": 200,
      "durationMs": 179,
      "responseSummary": {
        "dataLength": 0
      }
    },
    {
      "method": "GET",
      "path": "/order/da26033e-9e6d-48b3-9129-c96a2adf09c6/service",
      "status": 200,
      "durationMs": 178,
      "responseSummary": {
        "dataLength": 1
      }
    },
    {
      "method": "GET",
      "path": "/order/da2e6cee-d0d1-4421-8482-dfe3372bdf6e/service",
      "status": 200,
      "durationMs": 176,
      "responseSummary": {
        "dataLength": 0
      }
    },
    {
      "method": "GET",
      "path": "/order/da395b52-92ae-4a33-953f-919875692f4e/service",
      "status": 200,
      "durationMs": 170,
      "responseSummary": {
        "dataLength": 1
      }
    },
    {
      "method": "GET",
      "path": "/order/da402c1c-63db-4242-af9c-47d44f625202/service",
      "status": 200,
      "durationMs": 186,
      "responseSummary": {
        "dataLength": 1
      }
    },
    {
      "method": "GET",
      "path": "/order/da4ae50a-11f6-4907-9044-14b6cfb4842b/service",
      "status": 200,
      "durationMs": 168,
      "responseSummary": {
        "dataLength": 2
      }
    },
    {
      "method": "GET",
      "path": "/order/da4f944f-7b26-4a53-a1a4-4d9560ede45b/service",
      "status": 200,
      "durationMs": 170,
      "responseSummary": {
        "dataLength": 0
      }
    },
    {
      "method": "GET",
      "path": "/order/da5a87af-476c-42ed-ab0b-eab28bc809c0/service",
      "status": 200,
      "durationMs": 170,
      "responseSummary": {
        "dataLength": 0
      }
    },
    {
      "method": "GET",
      "path": "/order/da679274-3c7a-466a-b9c3-59e4bcfbe2b4/service",
      "status": 200,
      "durationMs": 178,
      "responseSummary": {
        "dataLength": 1
      }
    },
    {
      "method": "GET",
      "path": "/order/da76f5d5-6d9e-4849-b513-5e5908f18b5a/service",
      "status": 200,
      "durationMs": 178,
      "responseSummary": {
        "dataLength": 0
      }
    },
    {
      "method": "GET",
      "path": "/order/da7a969f-f73f-42b6-9ec2-3a3f9e68e2cc/service",
      "status": 200,
      "durationMs": 175,
      "responseSummary": {
        "dataLength": 3
      }
    },
    {
      "method": "GET",
      "path": "/order/da7b9eca-c3b5-460f-997c-822a8b34a82c/service",
      "status": 200,
      "durationMs": 166,
      "responseSummary": {
        "dataLength": 2
      }
    },
    {
      "method": "GET",
      "path": "/order/da8607c9-ade7-4194-810a-aec0d8dfc4f1/service",
      "status": 200,
      "durationMs": 176,
      "responseSummary": {
        "dataLength": 3
      }
    },
    {
      "method": "GET",
      "path": "/order/da96cd7b-9178-4afe-8a4a-76917281fbc9/service",
      "status": 200,
      "durationMs": 195,
      "responseSummary": {
        "dataLength": 0
      }
    },
    {
      "method": "GET",
      "path": "/order/da9a7b85-3308-4bfe-9f4c-a5b8a0c9a9fc/service",
      "status": 200,
      "durationMs": 212,
      "responseSummary": {
        "dataLength": 1
      }
    },
    {
      "method": "GET",
      "path": "/order/da9fc826-4b41-4eb1-aab5-3af988fdfc6f/service",
      "status": 200,
      "durationMs": 187,
      "responseSummary": {
        "dataLength": 3
      }
    },
    {
      "method": "GET",
      "path": "/order/dac33fcb-a6d2-4fc7-bc52-c8a8df9b3f1b/service",
      "status": 200,
      "durationMs": 188,
      "responseSummary": {
        "dataLength": 1
      }
    },
    {
      "method": "GET",
      "path": "/order/dac6ac77-f6ec-4f36-899b-5132a7c9230c/service",
      "status": 200,
      "durationMs": 183,
      "responseSummary": {
        "dataLength": 1
      }
    },
    {
      "method": "GET",
      "path": "/order/dad01bf9-6909-41cf-94bf-80883a8416f2/service",
      "status": 200,
      "durationMs": 171,
      "responseSummary": {
        "dataLength": 5
      }
    },
    {
      "method": "GET",
      "path": "/order/dad0d734-ddc6-4e50-b81c-af8289e1f045/service",
      "status": 200,
      "durationMs": 173,
      "responseSummary": {
        "dataLength": 3
      }
    },
    {
      "method": "GET",
      "path": "/order/dae1c7b5-c33c-4cf4-a89f-2ab11e508bb4/service",
      "status": 200,
      "durationMs": 157,
      "responseSummary": {
        "dataLength": 1
      }
    },
    {
      "method": "GET",
      "path": "/order/db05d85e-09d1-4317-b1ff-5679d236d9d0/service",
      "status": 200,
      "durationMs": 171,
      "responseSummary": {
        "dataLength": 1
      }
    },
    {
      "method": "GET",
      "path": "/order/db0cde62-de29-4335-83ee-38029a2e607a/service",
      "status": 200,
      "durationMs": 1867,
      "responseSummary": {
        "dataLength": 1
      }
    },
    {
      "method": "GET",
      "path": "/order/db0d029a-868c-4a72-930d-535f117f9cd5/service",
      "status": 200,
      "durationMs": 169,
      "responseSummary": {
        "dataLength": 1
      }
    },
    {
      "method": "GET",
      "path": "/order/db13ee10-61b2-486d-8c4a-e5ba1ceef2c4/service",
      "status": 200,
      "durationMs": 260,
      "responseSummary": {
        "dataLength": 0
      }
    },
    {
      "method": "GET",
      "path": "/order/db30d2b0-9c4c-4119-93f2-df581eb42494/service",
      "status": 200,
      "durationMs": 288,
      "responseSummary": {
        "dataLength": 1
      }
    },
    {
      "method": "GET",
      "path": "/order/db3a1685-fa74-43c1-bb5e-7513f151f7dc/service",
      "status": 200,
      "durationMs": 160,
      "responseSummary": {
        "dataLength": 1
      }
    },
    {
      "method": "GET",
      "path": "/order/db4608bd-bd9a-498b-b94e-74e1a015b4f9/service",
      "status": 200,
      "durationMs": 170,
      "responseSummary": {
        "dataLength": 1
      }
    },
    {
      "method": "GET",
      "path": "/order/db51fbbb-5c9d-4e32-a2eb-82a40cecf62b/service",
      "status": 200,
      "durationMs": 171,
      "responseSummary": {
        "dataLength": 1
      }
    },
    {
      "method": "GET",
      "path": "/order/644cb1d2-893f-476a-bf5c-8f3c7e6b93bd/service",
      "status": 200,
      "durationMs": 164,
      "responseSummary": {
        "dataLength": 1
      }
    },
    {
      "method": "GET",
      "path": "/order/665d4102-8995-42ab-ad9a-76f135920c9a/service",
      "status": 200,
      "durationMs": 167,
      "responseSummary": {
        "dataLength": 0
      }
    },
    {
      "method": "GET",
      "path": "/order/6426d563-2b3d-401e-a675-6ea96385ceb9/service",
      "status": 200,
      "durationMs": 208,
      "responseSummary": {
        "dataLength": 0
      }
    },
    {
      "method": "GET",
      "path": "/order/642d03cb-f4be-41d1-9213-2c3cc62c47b6/service",
      "status": 200,
      "durationMs": 172,
      "responseSummary": {
        "dataLength": 2
      }
    },
    {
      "method": "GET",
      "path": "/order/638e6e9b-b767-46b3-af9e-0c5b8abb23d0/service",
      "status": 200,
      "durationMs": 169,
      "responseSummary": {
        "dataLength": 0
      }
    },
    {
      "method": "GET",
      "path": "/order/628dd40f-a73d-49af-b780-d3c3af3f07de/service",
      "status": 200,
      "durationMs": 160,
      "responseSummary": {
        "dataLength": 3
      }
    },
    {
      "method": "GET",
      "path": "/order/628fd086-208e-4d02-b680-5dc704b00ff2/service",
      "status": 200,
      "durationMs": 156,
      "responseSummary": {
        "dataLength": 0
      }
    },
    {
      "method": "GET",
      "path": "/order/614674f5-d074-4dc3-8e75-8a28ad89355b/service",
      "status": 200,
      "durationMs": 175,
      "responseSummary": {
        "dataLength": 1
      }
    },
    {
      "method": "GET",
      "path": "/order/6148154d-2847-4e19-bdee-524727a21adc/service",
      "status": 200,
      "durationMs": 168,
      "responseSummary": {
        "dataLength": 1
      }
    },
    {
      "method": "GET",
      "path": "/order/63d36202-7184-46d6-89e1-9ec4218bfe7e/service",
      "status": 200,
      "durationMs": 174,
      "responseSummary": {
        "dataLength": 3
      }
    },
    {
      "method": "GET",
      "path": "/order/60c0dc95-a93b-40a0-9c8b-5e247de598a8/service",
      "status": 200,
      "durationMs": 164,
      "responseSummary": {
        "dataLength": 1
      }
    },
    {
      "method": "GET",
      "path": "/order/60d86083-0a4b-46ca-9d1e-a694a5e9cb62/service",
      "status": 200,
      "durationMs": 175,
      "responseSummary": {
        "dataLength": 0
      }
    },
    {
      "method": "GET",
      "path": "/order/a8d42975-2736-4f75-9753-63d3d868953a/service",
      "status": 200,
      "durationMs": 173,
      "responseSummary": {
        "dataLength": 1
      }
    },
    {
      "method": "GET",
      "path": "/order/a8e214b6-1738-4f26-a5a3-0e1ca859d09f/service",
      "status": 200,
      "durationMs": 178,
      "responseSummary": {
        "dataLength": 1
      }
    },
    {
      "method": "GET",
      "path": "/order/a8e44487-03da-456b-a7b5-9c84733a3a8c/service",
      "status": 200,
      "durationMs": 175,
      "responseSummary": {
        "dataLength": 1
      }
    },
    {
      "method": "GET",
      "path": "/order/c1cd2f05-fcb2-4e46-a05a-f6465f8dc28f/service",
      "status": 200,
      "durationMs": 181,
      "responseSummary": {
        "dataLength": 1
      }
    },
    {
      "method": "GET",
      "path": "/order/c1e6e691-6532-4bd9-87b9-60b4dc3db8b3/service",
      "status": 200,
      "durationMs": 174,
      "responseSummary": {
        "dataLength": 3
      }
    },
    {
      "method": "GET",
      "path": "/order/c1ef451e-5fae-4918-8e1a-2e0e1c66de66/service",
      "status": 200,
      "durationMs": 190,
      "responseSummary": {
        "dataLength": 3
      }
    },
    {
      "method": "GET",
      "path": "/order/c1efe652-f8f1-47c3-b775-63338596b907/service",
      "status": 200,
      "durationMs": 166,
      "responseSummary": {
        "dataLength": 1
      }
    },
    {
      "method": "GET",
      "path": "/order/c1f05c20-b137-4deb-a398-a6927f935872/service",
      "status": 200,
      "durationMs": 171,
      "responseSummary": {
        "dataLength": 1
      }
    },
    {
      "method": "GET",
      "path": "/order/c1f83116-594a-4f5d-b4a9-46dc7053b4e4/service",
      "status": 200,
      "durationMs": 165,
      "responseSummary": {
        "dataLength": 1
      }
    },
    {
      "method": "GET",
      "path": "/order/c204530d-15a2-4170-b8a9-b55edb889740/service",
      "status": 200,
      "durationMs": 168,
      "responseSummary": {
        "dataLength": 1
      }
    },
    {
      "method": "GET",
      "path": "/order/c219fdb3-f7f1-43a1-b056-900aa5fdb40b/service",
      "status": 200,
      "durationMs": 174,
      "responseSummary": {
        "dataLength": 1
      }
    },
    {
      "method": "GET",
      "path": "/order/c224081c-019f-43f5-8a0d-441ce5dbbd94/service",
      "status": 200,
      "durationMs": 204,
      "responseSummary": {
        "dataLength": 0
      }
    },
    {
      "method": "GET",
      "path": "/order/c2240da9-367f-46a6-8d71-072042432502/service",
      "status": 200,
      "durationMs": 424,
      "responseSummary": {
        "dataLength": 2
      }
    },
    {
      "method": "GET",
      "path": "/order/c23ac213-2d65-4f8e-9209-9edd909dc71c/service",
      "status": 200,
      "durationMs": 178,
      "responseSummary": {
        "dataLength": 2
      }
    },
    {
      "method": "GET",
      "path": "/order/c26191a8-3415-4fd6-aadb-c887a6713a76/service",
      "status": 200,
      "durationMs": 178,
      "responseSummary": {
        "dataLength": 2
      }
    },
    {
      "method": "GET",
      "path": "/order/c2661ca4-ed1c-44f8-94df-6e1690bb8cc3/service",
      "status": 200,
      "durationMs": 176,
      "responseSummary": {
        "dataLength": 0
      }
    },
    {
      "method": "GET",
      "path": "/order/c271b6ea-a2f1-461f-9bd7-3a5d1b8970c2/service",
      "status": 200,
      "durationMs": 175,
      "responseSummary": {
        "dataLength": 1
      }
    },
    {
      "method": "GET",
      "path": "/order/c2738a47-b1c9-4093-9d51-5a16a85c3cbb/service",
      "status": 200,
      "durationMs": 186,
      "responseSummary": {
        "dataLength": 1
      }
    },
    {
      "method": "GET",
      "path": "/order/c2839649-a9df-45e5-864f-275bd8e9c83f/service",
      "status": 200,
      "durationMs": 161,
      "responseSummary": {
        "dataLength": 3
      }
    },
    {
      "method": "GET",
      "path": "/order/a1664ffc-7a73-4e28-b3b9-1f19b8977644/service",
      "status": 200,
      "durationMs": 184,
      "responseSummary": {
        "dataLength": 2
      }
    },
    {
      "method": "GET",
      "path": "/order/a166d86f-fe33-4788-a809-2aff6d8f2f48/service",
      "status": 200,
      "durationMs": 169,
      "responseSummary": {
        "dataLength": 0
      }
    },
    {
      "method": "GET",
      "path": "/order/a1a02b00-225f-4509-aecc-61673ce43221/service",
      "status": 200,
      "durationMs": 190,
      "responseSummary": {
        "dataLength": 0
      }
    },
    {
      "method": "GET",
      "path": "/order/a1a65267-bd2a-47b6-81ae-7db9dcd1fda5/service",
      "status": 200,
      "durationMs": 192,
      "responseSummary": {
        "dataLength": 0
      }
    },
    {
      "method": "GET",
      "path": "/order/a1a94e9f-cf58-4018-973f-c6d4cc8603b5/service",
      "status": 200,
      "durationMs": 163,
      "responseSummary": {
        "dataLength": 0
      }
    },
    {
      "method": "GET",
      "path": "/order/a1ad0898-020a-4d1f-9223-b236987c9047/service",
      "status": 200,
      "durationMs": 176,
      "responseSummary": {
        "dataLength": 0
      }
    },
    {
      "method": "GET",
      "path": "/order/a1ba3337-532f-4d5f-abe0-eceabb7097c4/service",
      "status": 200,
      "durationMs": 171,
      "responseSummary": {
        "dataLength": 2
      }
    },
    {
      "method": "GET",
      "path": "/order/a1cff921-25a9-4817-9eed-6fbaabdd75b7/service",
      "status": 200,
      "durationMs": 162,
      "responseSummary": {
        "dataLength": 1
      }
    },
    {
      "method": "GET",
      "path": "/order/a1d644ca-0a6e-49b0-85ab-a20622a39c86/service",
      "status": 200,
      "durationMs": 164,
      "responseSummary": {
        "dataLength": 1
      }
    },
    {
      "method": "GET",
      "path": "/order/a1e4f051-ebf1-4b0a-9e8e-89f728e18295/service",
      "status": 200,
      "durationMs": 164,
      "responseSummary": {
        "dataLength": 1
      }
    },
    {
      "method": "GET",
      "path": "/order/a1e9183c-ea55-45a5-a4c8-0ae99c9ae2db/service",
      "status": 200,
      "durationMs": 162,
      "responseSummary": {
        "dataLength": 1
      }
    },
    {
      "method": "GET",
      "path": "/order/a1eeeb00-f8c8-455c-82e1-8f1bc1e706f8/service",
      "status": 200,
      "durationMs": 161,
      "responseSummary": {
        "dataLength": 0
      }
    },
    {
      "method": "GET",
      "path": "/order/a1f6eb75-941e-49de-822c-00dcbdeb9f24/service",
      "status": 200,
      "durationMs": 180,
      "responseSummary": {
        "dataLength": 1
      }
    },
    {
      "method": "GET",
      "path": "/order/a1fe49ce-f93e-4417-8ab3-933c624fb1ab/service",
      "status": 200,
      "durationMs": 166,
      "responseSummary": {
        "dataLength": 1
      }
    },
    {
      "method": "GET",
      "path": "/order/a2046d1e-d2d0-466f-9507-4e847b89d67b/service",
      "status": 200,
      "durationMs": 177,
      "responseSummary": {
        "dataLength": 4
      }
    },
    {
      "method": "GET",
      "path": "/order/e652b7e6-c287-41a3-afcb-6e2b8011d752/service",
      "status": 200,
      "durationMs": 158,
      "responseSummary": {
        "dataLength": 2
      }
    },
    {
      "method": "GET",
      "path": "/order/e6712f8a-0554-4879-aa31-7977accc8243/service",
      "status": 200,
      "durationMs": 167,
      "responseSummary": {
        "dataLength": 2
      }
    },
    {
      "method": "GET",
      "path": "/order/e67b192f-90a7-4b39-8913-bb46236949b5/service",
      "status": 200,
      "durationMs": 157,
      "responseSummary": {
        "dataLength": 1
      }
    },
    {
      "method": "GET",
      "path": "/order/e692147a-3be7-42c3-8588-101fd81beaf7/service",
      "status": 200,
      "durationMs": 174,
      "responseSummary": {
        "dataLength": 1
      }
    },
    {
      "method": "GET",
      "path": "/order/e6a22136-be03-456b-ad87-d47e9fb2f462/service",
      "status": 200,
      "durationMs": 165,
      "responseSummary": {
        "dataLength": 2
      }
    },
    {
      "method": "GET",
      "path": "/order/e6b3402d-9089-47d6-9859-e40ccfd21683/service",
      "status": 200,
      "durationMs": 167,
      "responseSummary": {
        "dataLength": 0
      }
    },
    {
      "method": "GET",
      "path": "/order/e6b9cc8c-f9dc-4559-88b8-75ab30abf9f5/service",
      "status": 200,
      "durationMs": 179,
      "responseSummary": {
        "dataLength": 1
      }
    },
    {
      "method": "GET",
      "path": "/order/e6d8286a-4fb2-4bf3-a53a-125185d49e0a/service",
      "status": 200,
      "durationMs": 172,
      "responseSummary": {
        "dataLength": 3
      }
    },
    {
      "method": "GET",
      "path": "/order/e6d8d7ac-9176-4616-8246-cc04ee164073/service",
      "status": 200,
      "durationMs": 169,
      "responseSummary": {
        "dataLength": 0
      }
    },
    {
      "method": "GET",
      "path": "/order/e6e0f68b-15e0-4827-885b-5c43e8d1fa29/service",
      "status": 200,
      "durationMs": 184,
      "responseSummary": {
        "dataLength": 0
      }
    },
    {
      "method": "GET",
      "path": "/order/e6e66924-43f3-4600-b794-c00acd69302a/service",
      "status": 200,
      "durationMs": 180,
      "responseSummary": {
        "dataLength": 0
      }
    },
    {
      "method": "GET",
      "path": "/order/e6ef6dc5-5bcb-424f-b513-818aee292e64/service",
      "status": 200,
      "durationMs": 157,
      "responseSummary": {
        "dataLength": 2
      }
    },
    {
      "method": "GET",
      "path": "/order/e6fc50e8-1a0c-4319-963c-5476af18b437/service",
      "status": 200,
      "durationMs": 161,
      "responseSummary": {
        "dataLength": 0
      }
    },
    {
      "method": "GET",
      "path": "/order/e701a799-295b-4c3a-9484-99065aec7793/service",
      "status": 200,
      "durationMs": 174,
      "responseSummary": {
        "dataLength": 1
      }
    },
    {
      "method": "GET",
      "path": "/order/e70cc0c2-4bbc-4ea8-9af0-69209bbea044/service",
      "status": 200,
      "durationMs": 213,
      "responseSummary": {
        "dataLength": 3
      }
    },
    {
      "method": "GET",
      "path": "/order/e70da17b-1479-4836-a205-9b8da513bf1c/service",
      "status": 200,
      "durationMs": 164,
      "responseSummary": {
        "dataLength": 7
      }
    },
    {
      "method": "GET",
      "path": "/order/e73afa86-e37b-478b-bd42-45afde2da71d/service",
      "status": 200,
      "durationMs": 166,
      "responseSummary": {
        "dataLength": 2
      }
    },
    {
      "method": "GET",
      "path": "/order/e74343f2-11c8-4d11-8bf9-909cd24d985b/service",
      "status": 200,
      "durationMs": 165,
      "responseSummary": {
        "dataLength": 4
      }
    },
    {
      "method": "GET",
      "path": "/order/e7506be6-0690-4d37-949f-0c44cdff9ee7/service",
      "status": 200,
      "durationMs": 196,
      "responseSummary": {
        "dataLength": 2
      }
    },
    {
      "method": "GET",
      "path": "/order/e7572f5e-3eec-4392-bed7-86cc79a23e23/service",
      "status": 200,
      "durationMs": 166,
      "responseSummary": {
        "dataLength": 1
      }
    },
    {
      "method": "GET",
      "path": "/order/e75b307e-bbb2-4644-84cb-f6b3000e62b7/service",
      "status": 200,
      "durationMs": 189,
      "responseSummary": {
        "dataLength": 1
      }
    },
    {
      "method": "GET",
      "path": "/order/e7603040-430f-4acb-9084-fd3d46bd9b40/service",
      "status": 200,
      "durationMs": 173,
      "responseSummary": {
        "dataLength": 2
      }
    },
    {
      "method": "GET",
      "path": "/order/e76ab698-b517-4d0d-89c5-c41092155665/service",
      "status": 200,
      "durationMs": 191,
      "responseSummary": {
        "dataLength": 4
      }
    },
    {
      "method": "GET",
      "path": "/order/e7729292-5cbd-4273-a416-3f6296dbd831/service",
      "status": 200,
      "durationMs": 163,
      "responseSummary": {
        "dataLength": 1
      }
    },
    {
      "method": "GET",
      "path": "/order/e778d803-1d8e-4ebe-ad4d-2f5545cb1421/service",
      "status": 200,
      "durationMs": 173,
      "responseSummary": {
        "dataLength": 1
      }
    },
    {
      "method": "GET",
      "path": "/order/e793f70e-dccb-4cd5-9bcd-61f709abfb02/service",
      "status": 200,
      "durationMs": 166,
      "responseSummary": {
        "dataLength": 1
      }
    },
    {
      "method": "GET",
      "path": "/order/e7950bd2-e219-4c7b-adb6-4c35b3211aab/service",
      "status": 200,
      "durationMs": 167,
      "responseSummary": {
        "dataLength": 1
      }
    },
    {
      "method": "GET",
      "path": "/order/e7a55a1d-25c7-45d2-8bb9-c240b454fc66/service",
      "status": 200,
      "durationMs": 177,
      "responseSummary": {
        "dataLength": 1
      }
    },
    {
      "method": "GET",
      "path": "/order/e7b139d8-f4aa-4c10-ba88-068415f15a07/service",
      "status": 200,
      "durationMs": 187,
      "responseSummary": {
        "dataLength": 1
      }
    },
    {
      "method": "GET",
      "path": "/order/face47da-9636-4820-af82-903659a75413/service",
      "status": 200,
      "durationMs": 177,
      "responseSummary": {
        "dataLength": 0
      }
    },
    {
      "method": "GET",
      "path": "/order/fad7b1aa-f413-400a-b7b9-bf7ae212fb37/service",
      "status": 200,
      "durationMs": 159,
      "responseSummary": {
        "dataLength": 1
      }
    },
    {
      "method": "GET",
      "path": "/order/fadb3b1b-57cd-46c5-b2f1-cdaa5fb56507/service",
      "status": 200,
      "durationMs": 180,
      "responseSummary": {
        "dataLength": 1
      }
    },
    {
      "method": "GET",
      "path": "/order/fadfc6be-a5b3-4804-94b4-516ba60f3cc9/service",
      "status": 200,
      "durationMs": 158,
      "responseSummary": {
        "dataLength": 1
      }
    },
    {
      "method": "GET",
      "path": "/order/fae1d953-1053-41e1-8dfd-9e97eab41d15/service",
      "status": 200,
      "durationMs": 171,
      "responseSummary": {
        "dataLength": 2
      }
    },
    {
      "method": "GET",
      "path": "/order/fae3348a-ddc4-4b6f-bd9b-add1e313867b/service",
      "status": 200,
      "durationMs": 206,
      "responseSummary": {
        "dataLength": 2
      }
    },
    {
      "method": "GET",
      "path": "/order/fae737b3-924f-4e88-969c-f624c304a7ef/service",
      "status": 200,
      "durationMs": 168,
      "responseSummary": {
        "dataLength": 0
      }
    },
    {
      "method": "GET",
      "path": "/order/fb05328e-7be9-4634-bbdd-7c985b96574e/service",
      "status": 200,
      "durationMs": 167,
      "responseSummary": {
        "dataLength": 2
      }
    },
    {
      "method": "GET",
      "path": "/order/fb176060-b066-4625-8aa1-eb283011b2d8/service",
      "status": 200,
      "durationMs": 184,
      "responseSummary": {
        "dataLength": 0
      }
    },
    {
      "method": "GET",
      "path": "/order/fb2012f0-6928-443a-b47c-bb6485dfb2c3/service",
      "status": 200,
      "durationMs": 234,
      "responseSummary": {
        "dataLength": 0
      }
    },
    {
      "method": "GET",
      "path": "/order/fb322f75-206d-40e9-871e-0f62075616f1/service",
      "status": 200,
      "durationMs": 172,
      "responseSummary": {
        "dataLength": 5
      }
    },
    {
      "method": "GET",
      "path": "/order/fb34e479-8794-4646-9967-173efafd25f2/service",
      "status": 200,
      "durationMs": 180,
      "responseSummary": {
        "dataLength": 0
      }
    },
    {
      "method": "GET",
      "path": "/order/fb3f7f81-6123-49c8-bdf0-14e268d054c8/service",
      "status": 200,
      "durationMs": 172,
      "responseSummary": {
        "dataLength": 1
      }
    },
    {
      "method": "GET",
      "path": "/order/fb4e3891-3524-42e4-9379-9ace5876ec1f/service",
      "status": 200,
      "durationMs": 178,
      "responseSummary": {
        "dataLength": 2
      }
    },
    {
      "method": "GET",
      "path": "/order/fb56f7e5-8ea1-4de6-8b1a-d31ee7bbbf6c/service",
      "status": 200,
      "durationMs": 165,
      "responseSummary": {
        "dataLength": 2
      }
    },
    {
      "method": "GET",
      "path": "/order/fb585726-b98f-4851-b699-2e3411720536/service",
      "status": 200,
      "durationMs": 175,
      "responseSummary": {
        "dataLength": 1
      }
    },
    {
      "method": "GET",
      "path": "/order/fb7734e3-3436-448d-9060-5df5caedf3a6/service",
      "status": 200,
      "durationMs": 168,
      "responseSummary": {
        "dataLength": 1
      }
    },
    {
      "method": "GET",
      "path": "/order/fb792570-478d-4d4c-801f-e86946b78d13/service",
      "status": 200,
      "durationMs": 169,
      "responseSummary": {
        "dataLength": 2
      }
    },
    {
      "method": "GET",
      "path": "/order/fb7f8e94-858c-4e8a-a966-71c968482dfa/service",
      "status": 200,
      "durationMs": 167,
      "responseSummary": {
        "dataLength": 1
      }
    },
    {
      "method": "GET",
      "path": "/order/fb828855-ba3b-4fb7-adaa-eb8bbc86b158/service",
      "status": 200,
      "durationMs": 176,
      "responseSummary": {
        "dataLength": 4
      }
    },
    {
      "method": "GET",
      "path": "/order/fb8f14f2-12b1-45f2-a211-3dcbad4df0bd/service",
      "status": 200,
      "durationMs": 194,
      "responseSummary": {
        "dataLength": 2
      }
    },
    {
      "method": "GET",
      "path": "/order/fb985a63-fdd0-4284-b4b9-0bbdba7db701/service",
      "status": 200,
      "durationMs": 171,
      "responseSummary": {
        "dataLength": 1
      }
    },
    {
      "method": "GET",
      "path": "/order/fb99220b-04b9-40de-ba1a-c9241dd577bf/service",
      "status": 200,
      "durationMs": 168,
      "responseSummary": {
        "dataLength": 1
      }
    },
    {
      "method": "GET",
      "path": "/order/fba86766-b932-40c5-9f46-fddfd2a77ea8/service",
      "status": 200,
      "durationMs": 171,
      "responseSummary": {
        "dataLength": 1
      }
    },
    {
      "method": "GET",
      "path": "/order/fbaff8e6-5ff9-4767-a59a-3bf2f1bd562b/service",
      "status": 200,
      "durationMs": 158,
      "responseSummary": {
        "dataLength": 1
      }
    },
    {
      "method": "GET",
      "path": "/order/fbb4c803-8a29-429e-aca5-aa93338a1dad/service",
      "status": 200,
      "durationMs": 161,
      "responseSummary": {
        "dataLength": 1
      }
    },
    {
      "method": "GET",
      "path": "/order/fbcd6b77-bc1d-49d4-8a42-c0db87cccfe7/service",
      "status": 200,
      "durationMs": 174,
      "responseSummary": {
        "dataLength": 1
      }
    },
    {
      "method": "GET",
      "path": "/order/fbe040f8-7bad-4606-9579-98d9360412a0/service",
      "status": 200,
      "durationMs": 183,
      "responseSummary": {
        "dataLength": 1
      }
    },
    {
      "method": "GET",
      "path": "/order/fbeb6d28-e7ec-43f3-b5a3-bf76d5578231/service",
      "status": 200,
      "durationMs": 153,
      "responseSummary": {
        "dataLength": 1
      }
    },
    {
      "method": "GET",
      "path": "/order/fbf9cad6-b27b-44fd-8c79-334fdb51e697/service",
      "status": 200,
      "durationMs": 178,
      "responseSummary": {
        "dataLength": 1
      }
    },
    {
      "method": "GET",
      "path": "/order/fbff6b9e-fe46-4680-b11c-e306902ed0ed/service",
      "status": 200,
      "durationMs": 180,
      "responseSummary": {
        "dataLength": 1
      }
    },
    {
      "method": "GET",
      "path": "/order/becad48a-7b7a-4bd2-9c47-bd0db7221130/service",
      "status": 200,
      "durationMs": 181,
      "responseSummary": {
        "dataLength": 1
      }
    },
    {
      "method": "GET",
      "path": "/order/bed18c04-0d8b-4f41-97e4-2cbaf5ea1d52/service",
      "status": 200,
      "durationMs": 161,
      "responseSummary": {
        "dataLength": 2
      }
    },
    {
      "method": "GET",
      "path": "/order/bed1b4bf-6437-488f-9a38-dd48a4128b6b/service",
      "status": 200,
      "durationMs": 186,
      "responseSummary": {
        "dataLength": 1
      }
    },
    {
      "method": "GET",
      "path": "/order/beeef555-b421-4808-8778-e4d09217d35b/service",
      "status": 200,
      "durationMs": 154,
      "responseSummary": {
        "dataLength": 0
      }
    },
    {
      "method": "GET",
      "path": "/order/bef14658-5257-4ed8-a560-06090c768eee/service",
      "status": 200,
      "durationMs": 169,
      "responseSummary": {
        "dataLength": 1
      }
    },
    {
      "method": "GET",
      "path": "/order/bf00d536-78dd-46ca-bd48-927fdac94cd6/service",
      "status": 200,
      "durationMs": 157,
      "responseSummary": {
        "dataLength": 2
      }
    },
    {
      "method": "GET",
      "path": "/order/bf03ee37-d70a-4b9a-8eab-ca5a885add1d/service",
      "status": 200,
      "durationMs": 216,
      "responseSummary": {
        "dataLength": 0
      }
    },
    {
      "method": "GET",
      "path": "/order/bf048bed-5796-43a1-a3c2-0174ce60b1d9/service",
      "status": 200,
      "durationMs": 174,
      "responseSummary": {
        "dataLength": 1
      }
    },
    {
      "method": "GET",
      "path": "/order/bf308c16-385a-41f0-b4e5-eb6d4254ff0e/service",
      "status": 200,
      "durationMs": 164,
      "responseSummary": {
        "dataLength": 0
      }
    },
    {
      "method": "GET",
      "path": "/order/bf4e1c25-d2e9-4edb-ae60-ae8d7bdd80d2/service",
      "status": 200,
      "durationMs": 177,
      "responseSummary": {
        "dataLength": 1
      }
    },
    {
      "method": "GET",
      "path": "/order/bf5a2169-6002-4766-a811-284d594124ea/service",
      "status": 200,
      "durationMs": 158,
      "responseSummary": {
        "dataLength": 1
      }
    },
    {
      "method": "GET",
      "path": "/order/bf67b70a-5ee6-4a32-96cd-b06222822dac/service",
      "status": 200,
      "durationMs": 167,
      "responseSummary": {
        "dataLength": 2
      }
    },
    {
      "method": "GET",
      "path": "/order/bf725a9a-c747-4063-aa73-af3a7edc0a3a/service",
      "status": 200,
      "durationMs": 173,
      "responseSummary": {
        "dataLength": 2
      }
    },
    {
      "method": "GET",
      "path": "/order/bf7a3a7d-1a92-49eb-8717-5b87ef9ea8de/service",
      "status": 200,
      "durationMs": 181,
      "responseSummary": {
        "dataLength": 1
      }
    },
    {
      "method": "GET",
      "path": "/order/bf9dbebe-99a9-451d-89ce-204be0d3f0e9/service",
      "status": 200,
      "durationMs": 166,
      "responseSummary": {
        "dataLength": 1
      }
    },
    {
      "method": "GET",
      "path": "/order/bfa18139-27a0-4ee5-a3f0-9070d86e18b7/service",
      "status": 200,
      "durationMs": 1841,
      "responseSummary": {
        "dataLength": 3
      }
    },
    {
      "method": "GET",
      "path": "/order/bfa2f80e-88b3-4ffc-b7b0-cc23b8f8182e/service",
      "status": 200,
      "durationMs": 157,
      "responseSummary": {
        "dataLength": 0
      }
    },
    {
      "method": "GET",
      "path": "/order/6407456d-3cd2-4581-a947-1f547bddddaf/service",
      "status": 200,
      "durationMs": 164,
      "responseSummary": {
        "dataLength": 1
      }
    },
    {
      "method": "GET",
      "path": "/order/98444be0-bcc1-44f7-8a6e-2f5a6eeadcb2/service",
      "status": 200,
      "durationMs": 174,
      "responseSummary": {
        "dataLength": 1
      }
    },
    {
      "method": "GET",
      "path": "/order/9847c8eb-f924-41c1-9c58-90c2d762f33a/service",
      "status": 200,
      "durationMs": 166,
      "responseSummary": {
        "dataLength": 0
      }
    },
    {
      "method": "GET",
      "path": "/order/984baaf2-f3cd-4420-97b9-eeb6ff07e4bd/service",
      "status": 200,
      "durationMs": 182,
      "responseSummary": {
        "dataLength": 2
      }
    },
    {
      "method": "GET",
      "path": "/order/9857a078-997d-4527-886d-df1526bb239e/service",
      "status": 200,
      "durationMs": 151,
      "responseSummary": {
        "dataLength": 1
      }
    },
    {
      "method": "GET",
      "path": "/order/f8c35cc5-490f-4dcf-ad78-6093c743a9f7/service",
      "status": 200,
      "durationMs": 262,
      "responseSummary": {
        "dataLength": 1
      }
    },
    {
      "method": "GET",
      "path": "/order/f8cc1fae-33bf-4eed-894f-ae474991a80d/service",
      "status": 200,
      "durationMs": 167,
      "responseSummary": {
        "dataLength": 1
      }
    },
    {
      "method": "GET",
      "path": "/order/f8d395f0-9a5c-4aec-8464-04cf4379323d/service",
      "status": 200,
      "durationMs": 175,
      "responseSummary": {
        "dataLength": 0
      }
    },
    {
      "method": "GET",
      "path": "/order/789279a3-dea0-42fe-9bd1-7507d3723190/service",
      "status": 200,
      "durationMs": 169,
      "responseSummary": {
        "dataLength": 0
      }
    },
    {
      "method": "GET",
      "path": "/order/7893603e-9fe2-426b-b7d7-471a947b916d/service",
      "status": 200,
      "durationMs": 178,
      "responseSummary": {
        "dataLength": 2
      }
    },
    {
      "method": "GET",
      "path": "/order/789549d8-84f5-4c49-8e47-01aa285003fd/service",
      "status": 200,
      "durationMs": 188,
      "responseSummary": {
        "dataLength": 2
      }
    },
    {
      "method": "GET",
      "path": "/order/78b11f51-59d8-4264-90f4-012a209ecc6d/service",
      "status": 200,
      "durationMs": 187,
      "responseSummary": {
        "dataLength": 0
      }
    },
    {
      "method": "GET",
      "path": "/order/78b57813-d418-4d8c-8dc1-4893a4fdc2e2/service",
      "status": 200,
      "durationMs": 175,
      "responseSummary": {
        "dataLength": 2
      }
    },
    {
      "method": "GET",
      "path": "/order/78c1049c-8c9b-4787-88b4-40e3bbed4cac/service",
      "status": 200,
      "durationMs": 174,
      "responseSummary": {
        "dataLength": 5
      }
    },
    {
      "method": "GET",
      "path": "/order/78c483af-90c0-438c-bbdd-673e7c72638f/service",
      "status": 200,
      "durationMs": 170,
      "responseSummary": {
        "dataLength": 1
      }
    },
    {
      "method": "GET",
      "path": "/order/78d96769-f4de-4b54-8792-818bf6c83e67/service",
      "status": 200,
      "durationMs": 173,
      "responseSummary": {
        "dataLength": 3
      }
    },
    {
      "method": "GET",
      "path": "/order/78dff7c0-f1b6-4bc4-9fed-30e4bd73a88a/service",
      "status": 200,
      "durationMs": 203,
      "responseSummary": {
        "dataLength": 1
      }
    },
    {
      "method": "GET",
      "path": "/order/78e22993-94bb-44ce-86b6-80163b3437b2/service",
      "status": 200,
      "durationMs": 209,
      "responseSummary": {
        "dataLength": 2
      }
    },
    {
      "method": "GET",
      "path": "/order/78e4da11-09f9-4615-8597-61da73e6d1b5/service",
      "status": 200,
      "durationMs": 213,
      "responseSummary": {
        "dataLength": 1
      }
    },
    {
      "method": "GET",
      "path": "/order/78e6c054-e4a0-45cd-9af5-409a4dabe541/service",
      "status": 200,
      "durationMs": 239,
      "responseSummary": {
        "dataLength": 1
      }
    },
    {
      "method": "GET",
      "path": "/order/78f12dd1-ee78-4aad-92d0-edeacd33c4ec/service",
      "status": 200,
      "durationMs": 246,
      "responseSummary": {
        "dataLength": 1
      }
    },
    {
      "method": "GET",
      "path": "/order/791527c6-2374-4df3-9083-561f10078c0d/service",
      "status": 200,
      "durationMs": 225,
      "responseSummary": {
        "dataLength": 3
      }
    },
    {
      "method": "GET",
      "path": "/order/7922edd6-8335-49b2-8e77-fbd8f04b55f7/service",
      "status": 200,
      "durationMs": 207,
      "responseSummary": {
        "dataLength": 1
      }
    },
    {
      "method": "GET",
      "path": "/order/792ff9c8-3712-40ff-8ed3-e2450e22c0da/service",
      "status": 200,
      "durationMs": 183,
      "responseSummary": {
        "dataLength": 1
      }
    },
    {
      "method": "GET",
      "path": "/order/7937b1af-3815-46b0-a7de-fa308cf60848/service",
      "status": 200,
      "durationMs": 176,
      "responseSummary": {
        "dataLength": 3
      }
    },
    {
      "method": "GET",
      "path": "/order/795e3b23-be89-4c27-9c42-7240049fd081/service",
      "status": 200,
      "durationMs": 173,
      "responseSummary": {
        "dataLength": 1
      }
    },
    {
      "method": "GET",
      "path": "/order/79641cc8-8169-4453-ab4c-ab4f653a9ab6/service",
      "status": 200,
      "durationMs": 165,
      "responseSummary": {
        "dataLength": 0
      }
    },
    {
      "method": "GET",
      "path": "/order/796bf709-18cb-4dbf-b600-27de8ba20634/service",
      "status": 200,
      "durationMs": 195,
      "responseSummary": {
        "dataLength": 2
      }
    },
    {
      "method": "GET",
      "path": "/order/7976b76f-394e-4b6e-a97f-39b273946bef/service",
      "status": 200,
      "durationMs": 182,
      "responseSummary": {
        "dataLength": 1
      }
    },
    {
      "method": "GET",
      "path": "/order/797d9595-7ed3-4752-bdad-d6d86732902d/service",
      "status": 200,
      "durationMs": 162,
      "responseSummary": {
        "dataLength": 2
      }
    },
    {
      "method": "GET",
      "path": "/order/79999485-fcc1-4b0d-9f52-44523d0e759a/service",
      "status": 200,
      "durationMs": 182,
      "responseSummary": {
        "dataLength": 2
      }
    },
    {
      "method": "GET",
      "path": "/order/799f77e8-9f27-40b5-8a3a-ca732b8b280b/service",
      "status": 200,
      "durationMs": 182,
      "responseSummary": {
        "dataLength": 4
      }
    },
    {
      "method": "GET",
      "path": "/order/79b13490-eb1f-4a57-a086-15b80b6249bd/service",
      "status": 200,
      "durationMs": 170,
      "responseSummary": {
        "dataLength": 2
      }
    },
    {
      "method": "GET",
      "path": "/order/63ab77a3-f153-41e7-a70e-89bef95a781d/service",
      "status": 200,
      "durationMs": 157,
      "responseSummary": {
        "dataLength": 1
      }
    },
    {
      "method": "GET",
      "path": "/order/95d6056d-116f-447d-9ecb-4421dc5729f3/service",
      "status": 200,
      "durationMs": 160,
      "responseSummary": {
        "dataLength": 2
      }
    },
    {
      "method": "GET",
      "path": "/order/95d814d1-6f07-4a66-88da-151a7af8c993/service",
      "status": 200,
      "durationMs": 170,
      "responseSummary": {
        "dataLength": 3
      }
    },
    {
      "method": "GET",
      "path": "/order/95e8ee14-158a-479b-8c17-0b9148f451e3/service",
      "status": 200,
      "durationMs": 169,
      "responseSummary": {
        "dataLength": 3
      }
    },
    {
      "method": "GET",
      "path": "/order/95ed4000-89ec-47de-bc2b-38fef236d91c/service",
      "status": 200,
      "durationMs": 161,
      "responseSummary": {
        "dataLength": 0
      }
    },
    {
      "method": "GET",
      "path": "/order/95f77208-9ee5-42c9-b882-99f309cb9e67/service",
      "status": 200,
      "durationMs": 185,
      "responseSummary": {
        "dataLength": 2
      }
    },
    {
      "method": "GET",
      "path": "/order/95fb4358-e436-4a85-a947-5e751761d0fe/service",
      "status": 200,
      "durationMs": 180,
      "responseSummary": {
        "dataLength": 1
      }
    },
    {
      "method": "GET",
      "path": "/order/9607630c-18d3-4e78-ae05-ab1d81ed3562/service",
      "status": 200,
      "durationMs": 180,
      "responseSummary": {
        "dataLength": 2
      }
    },
    {
      "method": "GET",
      "path": "/order/960a22f7-ccb6-4934-8cf7-41c281e65e8c/service",
      "status": 200,
      "durationMs": 159,
      "responseSummary": {
        "dataLength": 0
      }
    },
    {
      "method": "GET",
      "path": "/order/9612d778-9686-405a-a1ed-3a3cee2962be/service",
      "status": 200,
      "durationMs": 167,
      "responseSummary": {
        "dataLength": 2
      }
    },
    {
      "method": "GET",
      "path": "/order/961725c5-e8b9-4e3f-9f31-d81a3ac4bf18/service",
      "status": 200,
      "durationMs": 198,
      "responseSummary": {
        "dataLength": 0
      }
    },
    {
      "method": "GET",
      "path": "/order/961743de-974b-45b8-bc3b-096937fda18b/service",
      "status": 200,
      "durationMs": 170,
      "responseSummary": {
        "dataLength": 1
      }
    },
    {
      "method": "GET",
      "path": "/order/9623c25f-819b-49df-a04a-224968bf2352/service",
      "status": 200,
      "durationMs": 185,
      "responseSummary": {
        "dataLength": 0
      }
    },
    {
      "method": "GET",
      "path": "/order/96343ed4-d874-4b42-a822-163509e6a1b4/service",
      "status": 200,
      "durationMs": 161,
      "responseSummary": {
        "dataLength": 0
      }
    },
    {
      "method": "GET",
      "path": "/order/9635733c-26ba-436f-95ae-c3f063d9c727/service",
      "status": 200,
      "durationMs": 186,
      "responseSummary": {
        "dataLength": 1
      }
    },
    {
      "method": "GET",
      "path": "/order/96438745-1a56-487f-82dd-326c395b53a7/service",
      "status": 200,
      "durationMs": 198,
      "responseSummary": {
        "dataLength": 1
      }
    },
    {
      "method": "GET",
      "path": "/order/9646adaf-6de6-4b72-8764-a39715a8b037/service",
      "status": 200,
      "durationMs": 170,
      "responseSummary": {
        "dataLength": 1
      }
    },
    {
      "method": "GET",
      "path": "/order/965c84e2-3e0a-4074-9405-f5281813850a/service",
      "status": 200,
      "durationMs": 173,
      "responseSummary": {
        "dataLength": 2
      }
    },
    {
      "method": "GET",
      "path": "/order/96602160-83bf-40f8-a8c7-4740281edbdf/service",
      "status": 200,
      "durationMs": 183,
      "responseSummary": {
        "dataLength": 1
      }
    },
    {
      "method": "GET",
      "path": "/order/96646681-54ee-40b5-99e3-b7738a669da6/service",
      "status": 200,
      "durationMs": 156,
      "responseSummary": {
        "dataLength": 1
      }
    },
    {
      "method": "GET",
      "path": "/order/96786d55-e204-43ea-b360-7f599883af7b/service",
      "status": 200,
      "durationMs": 180,
      "responseSummary": {
        "dataLength": 0
      }
    },
    {
      "method": "GET",
      "path": "/order/96a21fd2-d418-461a-a2f7-a0ed63aa62be/service",
      "status": 200,
      "durationMs": 169,
      "responseSummary": {
        "dataLength": 1
      }
    },
    {
      "method": "GET",
      "path": "/order/96af1cd8-e2ba-42bb-8b57-1041772f61a5/service",
      "status": 200,
      "durationMs": 167,
      "responseSummary": {
        "dataLength": 0
      }
    },
    {
      "method": "GET",
      "path": "/order/96b14dc6-f745-4bb9-92f3-24488df0942d/service",
      "status": 200,
      "durationMs": 188,
      "responseSummary": {
        "dataLength": 3
      }
    },
    {
      "method": "GET",
      "path": "/order/96b164da-98ca-4bed-b384-1e5a7d7941b0/service",
      "status": 200,
      "durationMs": 183,
      "responseSummary": {
        "dataLength": 1
      }
    },
    {
      "method": "GET",
      "path": "/order/96bcee3b-3cb1-4c59-88b4-139ffba6531e/service",
      "status": 200,
      "durationMs": 194,
      "responseSummary": {
        "dataLength": 1
      }
    },
    {
      "method": "GET",
      "path": "/order/96d7e385-6a4b-4d39-9eae-87a6dbeb326b/service",
      "status": 200,
      "durationMs": 172,
      "responseSummary": {
        "dataLength": 1
      }
    },
    {
      "method": "GET",
      "path": "/order/96ead890-28b4-446d-b728-fea20b350e51/service",
      "status": 200,
      "durationMs": 218,
      "responseSummary": {
        "dataLength": 1
      }
    },
    {
      "method": "GET",
      "path": "/order/96f8c26c-b2ba-4be2-895a-a9231713ab95/service",
      "status": 200,
      "durationMs": 176,
      "responseSummary": {
        "dataLength": 1
      }
    },
    {
      "method": "GET",
      "path": "/order/96facd76-a0eb-4a62-9dea-1113608946d6/service",
      "status": 200,
      "durationMs": 169,
      "responseSummary": {
        "dataLength": 2
      }
    },
    {
      "method": "GET",
      "path": "/order/970af0b6-2e3e-4bc9-ab9f-d742ea9a481f/service",
      "status": 200,
      "durationMs": 155,
      "responseSummary": {
        "dataLength": 0
      }
    },
    {
      "method": "GET",
      "path": "/order/9711a0ae-ece0-427f-9f12-c70e7aae5dc7/service",
      "status": 200,
      "durationMs": 178,
      "responseSummary": {
        "dataLength": 2
      }
    },
    {
      "method": "GET",
      "path": "/order/9723f627-fdee-4f51-a040-5fe19d7e8042/service",
      "status": 200,
      "durationMs": 185,
      "responseSummary": {
        "dataLength": 0
      }
    },
    {
      "method": "GET",
      "path": "/order/9724a872-b5cb-4c2e-82d2-a8d7ab218463/service",
      "status": 200,
      "durationMs": 192,
      "responseSummary": {
        "dataLength": 1
      }
    },
    {
      "method": "GET",
      "path": "/order/9739a1a3-0257-4f24-b434-cc766bd7d3f1/service",
      "status": 200,
      "durationMs": 175,
      "responseSummary": {
        "dataLength": 1
      }
    },
    {
      "method": "GET",
      "path": "/order/9741d7af-95f3-403c-9e27-1b0ae7c5f4ba/service",
      "status": 200,
      "durationMs": 177,
      "responseSummary": {
        "dataLength": 1
      }
    },
    {
      "method": "GET",
      "path": "/order/802426b4-16cb-4498-ab82-b236ba67ddf6/service",
      "status": 200,
      "durationMs": 179,
      "responseSummary": {
        "dataLength": 3
      }
    },
    {
      "method": "GET",
      "path": "/order/802eee39-96c5-49b1-8581-111766ddbe22/service",
      "status": 200,
      "durationMs": 169,
      "responseSummary": {
        "dataLength": 1
      }
    },
    {
      "method": "GET",
      "path": "/order/803a632b-4b64-43f0-936a-821d62380a98/service",
      "status": 200,
      "durationMs": 163,
      "responseSummary": {
        "dataLength": 1
      }
    },
    {
      "method": "GET",
      "path": "/order/8040070b-b63b-4d95-9bab-980f627be45f/service",
      "status": 200,
      "durationMs": 178,
      "responseSummary": {
        "dataLength": 1
      }
    },
    {
      "method": "GET",
      "path": "/order/80462025-469d-40ad-acce-97f911302a5f/service",
      "status": 200,
      "durationMs": 185,
      "responseSummary": {
        "dataLength": 1
      }
    },
    {
      "method": "GET",
      "path": "/order/8050a3c4-16b7-4fda-a340-f2c35121f897/service",
      "status": 200,
      "durationMs": 159,
      "responseSummary": {
        "dataLength": 3
      }
    },
    {
      "method": "GET",
      "path": "/order/80516b90-5528-4bcb-ae27-e712d48a5dd0/service",
      "status": 200,
      "durationMs": 177,
      "responseSummary": {
        "dataLength": 0
      }
    },
    {
      "method": "GET",
      "path": "/order/8053ea51-c449-4d93-b81b-a2adaa404e84/service",
      "status": 200,
      "durationMs": 173,
      "responseSummary": {
        "dataLength": 1
      }
    },
    {
      "method": "GET",
      "path": "/order/8057afb4-743b-4661-9064-5be11562a625/service",
      "status": 200,
      "durationMs": 180,
      "responseSummary": {
        "dataLength": 1
      }
    },
    {
      "method": "GET",
      "path": "/order/8063f338-d0fa-4f35-b5b1-d58e41c3a08e/service",
      "status": 200,
      "durationMs": 186,
      "responseSummary": {
        "dataLength": 1
      }
    },
    {
      "method": "GET",
      "path": "/order/807996fd-0583-4431-9c7c-62118fb2ec3f/service",
      "status": 200,
      "durationMs": 174,
      "responseSummary": {
        "dataLength": 4
      }
    },
    {
      "method": "GET",
      "path": "/order/807b459a-3069-4058-a710-2400015680ba/service",
      "status": 200,
      "durationMs": 186,
      "responseSummary": {
        "dataLength": 1
      }
    },
    {
      "method": "GET",
      "path": "/order/807bd4b8-2521-4533-b6f8-21598f4ab7ab/service",
      "status": 200,
      "durationMs": 163,
      "responseSummary": {
        "dataLength": 1
      }
    },
    {
      "method": "GET",
      "path": "/order/808e36c2-dcfb-454a-a5a5-547e448dd9f9/service",
      "status": 200,
      "durationMs": 179,
      "responseSummary": {
        "dataLength": 2
      }
    },
    {
      "method": "GET",
      "path": "/order/808f5624-5879-4277-a730-4b8f850de39a/service",
      "status": 200,
      "durationMs": 169,
      "responseSummary": {
        "dataLength": 1
      }
    },
    {
      "method": "GET",
      "path": "/order/8095221e-65ca-4bd2-b337-d9106a394f7b/service",
      "status": 200,
      "durationMs": 176,
      "responseSummary": {
        "dataLength": 1
      }
    },
    {
      "method": "GET",
      "path": "/order/809f7f9a-0ce6-47ab-bebd-de47af68a4fa/service",
      "status": 200,
      "durationMs": 154,
      "responseSummary": {
        "dataLength": 1
      }
    },
    {
      "method": "GET",
      "path": "/order/80b94903-2a51-4458-901a-2e6705028c82/service",
      "status": 200,
      "durationMs": 169,
      "responseSummary": {
        "dataLength": 1
      }
    },
    {
      "method": "GET",
      "path": "/order/80bf4f03-c575-4237-b7f8-514755ccca34/service",
      "status": 200,
      "durationMs": 168,
      "responseSummary": {
        "dataLength": 1
      }
    },
    {
      "method": "GET",
      "path": "/order/80c07fa3-84f9-4fb5-a1cb-870b416839f7/service",
      "status": 200,
      "durationMs": 213,
      "responseSummary": {
        "dataLength": 2
      }
    },
    {
      "method": "GET",
      "path": "/order/80cbce10-cced-44d3-90f4-f61e936a3005/service",
      "status": 200,
      "durationMs": 171,
      "responseSummary": {
        "dataLength": 1
      }
    },
    {
      "method": "GET",
      "path": "/order/80d73d18-073a-44ad-a565-eadb691016fd/service",
      "status": 200,
      "durationMs": 187,
      "responseSummary": {
        "dataLength": 1
      }
    },
    {
      "method": "GET",
      "path": "/order/80e09ab1-9596-4bb5-a0e6-504a03d4ea43/service",
      "status": 200,
      "durationMs": 163,
      "responseSummary": {
        "dataLength": 1
      }
    },
    {
      "method": "GET",
      "path": "/order/80e0ee48-7402-46cf-a1b2-68a897de8f4a/service",
      "status": 200,
      "durationMs": 166,
      "responseSummary": {
        "dataLength": 1
      }
    },
    {
      "method": "GET",
      "path": "/order/80e3219c-d99b-496e-9c60-d0dd9f73529e/service",
      "status": 200,
      "durationMs": 159,
      "responseSummary": {
        "dataLength": 4
      }
    },
    {
      "method": "GET",
      "path": "/order/80e600b4-9e5e-45c6-9135-1b6a61e60fbb/service",
      "status": 200,
      "durationMs": 165,
      "responseSummary": {
        "dataLength": 1
      }
    },
    {
      "method": "GET",
      "path": "/order/80f364af-fdc3-499a-9b3e-5ebfde63d66c/service",
      "status": 200,
      "durationMs": 175,
      "responseSummary": {
        "dataLength": 2
      }
    },
    {
      "method": "GET",
      "path": "/order/810d2aea-609c-4092-b1c4-e0b4c6cd1b51/service",
      "status": 200,
      "durationMs": 167,
      "responseSummary": {
        "dataLength": 2
      }
    },
    {
      "method": "GET",
      "path": "/order/810eece6-e732-4ab5-b31f-88c818600b51/service",
      "status": 200,
      "durationMs": 161,
      "responseSummary": {
        "dataLength": 2
      }
    },
    {
      "method": "GET",
      "path": "/order/8112c8ca-7dcc-42d1-a8a6-85f212fb57eb/service",
      "status": 200,
      "durationMs": 191,
      "responseSummary": {
        "dataLength": 3
      }
    },
    {
      "method": "GET",
      "path": "/order/8118ccbf-b940-43e0-ac2d-feb7b870d583/service",
      "status": 200,
      "durationMs": 161,
      "responseSummary": {
        "dataLength": 1
      }
    },
    {
      "method": "GET",
      "path": "/order/811f511b-2c73-4ed2-a006-d66b542bda52/service",
      "status": 200,
      "durationMs": 175,
      "responseSummary": {
        "dataLength": 1
      }
    },
    {
      "method": "GET",
      "path": "/order/81255542-fa59-4fd9-818e-68ecf86c7b74/service",
      "status": 200,
      "durationMs": 171,
      "responseSummary": {
        "dataLength": 6
      }
    },
    {
      "method": "GET",
      "path": "/order/8133b50e-7aaa-4b8c-b706-37a8f7b2fe25/service",
      "status": 200,
      "durationMs": 182,
      "responseSummary": {
        "dataLength": 1
      }
    },
    {
      "method": "GET",
      "path": "/order/8134418a-790b-4b3d-9f48-7a97e731c866/service",
      "status": 200,
      "durationMs": 164,
      "responseSummary": {
        "dataLength": 1
      }
    },
    {
      "method": "GET",
      "path": "/order/814fcfbd-3c81-4fcf-a5ae-7e54a2d30307/service",
      "status": 200,
      "durationMs": 184,
      "responseSummary": {
        "dataLength": 3
      }
    },
    {
      "method": "GET",
      "path": "/order/6ee586dc-7150-4904-a664-03026730689e/service",
      "status": 200,
      "durationMs": 172,
      "responseSummary": {
        "dataLength": 1
      }
    },
    {
      "method": "GET",
      "path": "/order/6eee00dc-5089-419d-83a3-2fe61453a7b6/service",
      "status": 200,
      "durationMs": 165,
      "responseSummary": {
        "dataLength": 1
      }
    },
    {
      "method": "GET",
      "path": "/order/6eee4aab-9efd-4c39-b92f-70e8dfa9aeb6/service",
      "status": 200,
      "durationMs": 180,
      "responseSummary": {
        "dataLength": 1
      }
    },
    {
      "method": "GET",
      "path": "/order/59d8018c-2409-43f7-b656-388c2ba2df15/service",
      "status": 200,
      "durationMs": 187,
      "responseSummary": {
        "dataLength": 2
      }
    },
    {
      "method": "GET",
      "path": "/order/59d82758-17c3-42ea-92ca-4efd3c96387c/service",
      "status": 200,
      "durationMs": 208,
      "responseSummary": {
        "dataLength": 0
      }
    },
    {
      "method": "GET",
      "path": "/order/59e34a7d-4f55-4b65-8ce3-d3adf7173bf7/service",
      "status": 200,
      "durationMs": 210,
      "responseSummary": {
        "dataLength": 7
      }
    },
    {
      "method": "GET",
      "path": "/order/59f9a7a7-67d2-4a0a-80a9-cd58d19c9c18/service",
      "status": 200,
      "durationMs": 168,
      "responseSummary": {
        "dataLength": 1
      }
    },
    {
      "method": "GET",
      "path": "/order/c3b3f0cc-3fcc-42a5-b7f3-b4d98aa8bf02/service",
      "status": 200,
      "durationMs": 204,
      "responseSummary": {
        "dataLength": 2
      }
    },
    {
      "method": "GET",
      "path": "/order/c3bbcc37-eff3-4a1b-9e4b-a01adfda2480/service",
      "status": 200,
      "durationMs": 171,
      "responseSummary": {
        "dataLength": 1
      }
    },
    {
      "method": "GET",
      "path": "/order/c3c32ef6-9674-4c86-9354-6ca05be95cca/service",
      "status": 200,
      "durationMs": 169,
      "responseSummary": {
        "dataLength": 0
      }
    },
    {
      "method": "GET",
      "path": "/order/c3c560a2-d9ad-4541-8ca4-a52497c36590/service",
      "status": 200,
      "durationMs": 181,
      "responseSummary": {
        "dataLength": 1
      }
    },
    {
      "method": "GET",
      "path": "/order/c3d1a5aa-0a74-41fb-85e1-f6e8da083e3a/service",
      "status": 200,
      "durationMs": 179,
      "responseSummary": {
        "dataLength": 1
      }
    },
    {
      "method": "GET",
      "path": "/order/c3eeac2f-75f7-4a08-bd99-d19fa69976e2/service",
      "status": 200,
      "durationMs": 163,
      "responseSummary": {
        "dataLength": 1
      }
    },
    {
      "method": "GET",
      "path": "/order/c3ef4003-609f-43eb-b5f1-e0072c668ea0/service",
      "status": 200,
      "durationMs": 182,
      "responseSummary": {
        "dataLength": 1
      }
    },
    {
      "method": "GET",
      "path": "/order/c411cc14-e2c1-4dcc-8119-728f82aadc8f/service",
      "status": 200,
      "durationMs": 164,
      "responseSummary": {
        "dataLength": 1
      }
    },
    {
      "method": "GET",
      "path": "/order/c4148c64-3e24-43f9-898a-b5d42faeeb74/service",
      "status": 200,
      "durationMs": 167,
      "responseSummary": {
        "dataLength": 3
      }
    },
    {
      "method": "GET",
      "path": "/order/c4186885-afea-495f-b6a7-62c23c9b496a/service",
      "status": 200,
      "durationMs": 167,
      "responseSummary": {
        "dataLength": 1
      }
    },
    {
      "method": "GET",
      "path": "/order/c41ed54f-2849-40fe-944a-d93096537f38/service",
      "status": 200,
      "durationMs": 180,
      "responseSummary": {
        "dataLength": 0
      }
    },
    {
      "method": "GET",
      "path": "/order/c424a1c3-a33e-4bd5-91d6-85ae34095d8b/service",
      "status": 200,
      "durationMs": 172,
      "responseSummary": {
        "dataLength": 1
      }
    },
    {
      "method": "GET",
      "path": "/order/c42a49ad-ee85-46cc-bd39-65f1e45f7d40/service",
      "status": 200,
      "durationMs": 175,
      "responseSummary": {
        "dataLength": 3
      }
    },
    {
      "method": "GET",
      "path": "/order/c43b0d48-448b-4271-b5e0-bfcbc151005b/service",
      "status": 200,
      "durationMs": 185,
      "responseSummary": {
        "dataLength": 1
      }
    },
    {
      "method": "GET",
      "path": "/order/c459841d-2cc9-408f-87d3-72cc7ed85283/service",
      "status": 200,
      "durationMs": 185,
      "responseSummary": {
        "dataLength": 2
      }
    },
    {
      "method": "GET",
      "path": "/order/c45cc065-d7a0-469a-90d5-92f265474a8f/service",
      "status": 200,
      "durationMs": 1835,
      "responseSummary": {
        "dataLength": 1
      }
    },
    {
      "method": "GET",
      "path": "/order/c4609554-d77a-45e3-a7d2-5051d5787cc5/service",
      "status": 200,
      "durationMs": 170,
      "responseSummary": {
        "dataLength": 1
      }
    },
    {
      "method": "GET",
      "path": "/order/c471e496-720c-4288-a27c-c315fb781477/service",
      "status": 200,
      "durationMs": 160,
      "responseSummary": {
        "dataLength": 1
      }
    },
    {
      "method": "GET",
      "path": "/order/c4733d2e-edda-4c3f-ab5a-17863e884c0e/service",
      "status": 200,
      "durationMs": 169,
      "responseSummary": {
        "dataLength": 1
      }
    },
    {
      "method": "GET",
      "path": "/order/c4746db9-b24d-4e0a-ae37-e8a59abdb49c/service",
      "status": 200,
      "durationMs": 157,
      "responseSummary": {
        "dataLength": 1
      }
    },
    {
      "method": "GET",
      "path": "/order/c47cc471-6911-4c76-b3f7-06596f9dd124/service",
      "status": 200,
      "durationMs": 169,
      "responseSummary": {
        "dataLength": 1
      }
    },
    {
      "method": "GET",
      "path": "/order/c48f76f8-f0e2-4a4c-a385-8c579a8be59a/service",
      "status": 200,
      "durationMs": 161,
      "responseSummary": {
        "dataLength": 1
      }
    },
    {
      "method": "GET",
      "path": "/order/cb5a8df3-7cd9-4cb5-bfbe-071190e2e2cf/service",
      "status": 200,
      "durationMs": 157,
      "responseSummary": {
        "dataLength": 0
      }
    },
    {
      "method": "GET",
      "path": "/order/cb5cd6a7-5214-4a7a-9f37-d969f4551a7e/service",
      "status": 200,
      "durationMs": 176,
      "responseSummary": {
        "dataLength": 2
      }
    },
    {
      "method": "GET",
      "path": "/order/cb67bb46-6101-4d00-b964-f5791114a80d/service",
      "status": 200,
      "durationMs": 174,
      "responseSummary": {
        "dataLength": 2
      }
    },
    {
      "method": "GET",
      "path": "/order/cb9675af-fce4-4fd7-bf8b-1d70c1c0cf51/service",
      "status": 200,
      "durationMs": 174,
      "responseSummary": {
        "dataLength": 1
      }
    },
    {
      "method": "GET",
      "path": "/order/cb9fe75c-298c-403f-9635-590ea1780dae/service",
      "status": 200,
      "durationMs": 180,
      "responseSummary": {
        "dataLength": 1
      }
    },
    {
      "method": "GET",
      "path": "/order/cba2435c-f275-4f30-828c-5b3fc96ac939/service",
      "status": 200,
      "durationMs": 188,
      "responseSummary": {
        "dataLength": 1
      }
    },
    {
      "method": "GET",
      "path": "/order/cbb378ce-3fef-4489-9d3a-85ea3e61ec07/service",
      "status": 200,
      "durationMs": 174,
      "responseSummary": {
        "dataLength": 1
      }
    },
    {
      "method": "GET",
      "path": "/order/cbb9d561-dd71-4a32-a952-b37bbb445f16/service",
      "status": 200,
      "durationMs": 176,
      "responseSummary": {
        "dataLength": 1
      }
    },
    {
      "method": "GET",
      "path": "/order/cbbb4dca-d164-4042-b39d-f9621acacd79/service",
      "status": 200,
      "durationMs": 206,
      "responseSummary": {
        "dataLength": 2
      }
    },
    {
      "method": "GET",
      "path": "/order/cbc05bba-2b35-4ec0-9372-e53d48138409/service",
      "status": 200,
      "durationMs": 202,
      "responseSummary": {
        "dataLength": 1
      }
    },
    {
      "method": "GET",
      "path": "/order/cbc98987-e2ca-429b-a99e-5808795873c6/service",
      "status": 200,
      "durationMs": 172,
      "responseSummary": {
        "dataLength": 4
      }
    },
    {
      "method": "GET",
      "path": "/order/cbcb297d-bfe2-4f33-9307-083ba8ee92b1/service",
      "status": 200,
      "durationMs": 177,
      "responseSummary": {
        "dataLength": 0
      }
    },
    {
      "method": "GET",
      "path": "/order/cbcf0992-f450-4ea2-ba0e-c94788eec690/service",
      "status": 200,
      "durationMs": 174,
      "responseSummary": {
        "dataLength": 0
      }
    },
    {
      "method": "GET",
      "path": "/order/cbcfd3d3-1ea9-4cbb-bd64-0ab18128af98/service",
      "status": 200,
      "durationMs": 166,
      "responseSummary": {
        "dataLength": 2
      }
    },
    {
      "method": "GET",
      "path": "/order/cbd2dbc4-3439-4ad9-91ce-12a49baf2eb5/service",
      "status": 200,
      "durationMs": 218,
      "responseSummary": {
        "dataLength": 2
      }
    },
    {
      "method": "GET",
      "path": "/order/cbdf3c3e-9f0d-4d0e-bcd7-dc5bc2cbe9c7/service",
      "status": 200,
      "durationMs": 180,
      "responseSummary": {
        "dataLength": 1
      }
    },
    {
      "method": "GET",
      "path": "/order/cbdf661e-0506-4825-8aad-bf963562cba2/service",
      "status": 200,
      "durationMs": 190,
      "responseSummary": {
        "dataLength": 1
      }
    },
    {
      "method": "GET",
      "path": "/order/cbe61710-a8d4-453f-8053-1d8ba97e4782/service",
      "status": 200,
      "durationMs": 318,
      "responseSummary": {
        "dataLength": 1
      }
    },
    {
      "method": "GET",
      "path": "/order/cbe64e0c-aa87-4cb4-bd20-74553055dd36/service",
      "status": 200,
      "durationMs": 232,
      "responseSummary": {
        "dataLength": 0
      }
    },
    {
      "method": "GET",
      "path": "/order/cbeff47e-95ee-4530-bfae-5172b28370dd/service",
      "status": 200,
      "durationMs": 220,
      "responseSummary": {
        "dataLength": 2
      }
    },
    {
      "method": "GET",
      "path": "/order/cc0485dc-25dc-4e06-ba55-776ddc8e6878/service",
      "status": 200,
      "durationMs": 194,
      "responseSummary": {
        "dataLength": 1
      }
    },
    {
      "method": "GET",
      "path": "/order/cc0c8d61-f4e7-4fcb-a020-b2373dfb02ca/service",
      "status": 200,
      "durationMs": 162,
      "responseSummary": {
        "dataLength": 2
      }
    },
    {
      "method": "GET",
      "path": "/order/cc195e43-eb6c-4869-ba48-40d00daa4580/service",
      "status": 200,
      "durationMs": 183,
      "responseSummary": {
        "dataLength": 1
      }
    },
    {
      "method": "GET",
      "path": "/order/cc1bf05e-92a4-4aa3-845b-1e5ec3b87e7f/service",
      "status": 200,
      "durationMs": 168,
      "responseSummary": {
        "dataLength": 0
      }
    },
    {
      "method": "GET",
      "path": "/order/cc37672f-70b4-46e6-a6f2-794efe8a6793/service",
      "status": 200,
      "durationMs": 175,
      "responseSummary": {
        "dataLength": 1
      }
    },
    {
      "method": "GET",
      "path": "/order/cc3c9f4a-debe-4c1c-adf6-58403d570cde/service",
      "status": 200,
      "durationMs": 168,
      "responseSummary": {
        "dataLength": 0
      }
    },
    {
      "method": "GET",
      "path": "/order/cc404ef6-2093-4874-8fdb-eb96d9b33b0f/service",
      "status": 200,
      "durationMs": 200,
      "responseSummary": {
        "dataLength": 1
      }
    },
    {
      "method": "GET",
      "path": "/order/cc413ee2-c49e-44e5-a1d1-e94a6eafaa81/service",
      "status": 200,
      "durationMs": 169,
      "responseSummary": {
        "dataLength": 1
      }
    },
    {
      "method": "GET",
      "path": "/order/cc4912e3-aa91-434e-98bd-1fcb079a31ee/service",
      "status": 200,
      "durationMs": 185,
      "responseSummary": {
        "dataLength": 2
      }
    },
    {
      "method": "GET",
      "path": "/order/cc4e597b-769b-49d5-a50d-31941307617d/service",
      "status": 200,
      "durationMs": 176,
      "responseSummary": {
        "dataLength": 0
      }
    },
    {
      "method": "GET",
      "path": "/order/d7b8a7e7-5ed8-4aca-ac2a-445f38dbae0b/service",
      "status": 200,
      "durationMs": 172,
      "responseSummary": {
        "dataLength": 1
      }
    },
    {
      "method": "GET",
      "path": "/order/d7e9f43a-a86d-461b-abbe-eb5616e8917b/service",
      "status": 200,
      "durationMs": 174,
      "responseSummary": {
        "dataLength": 5
      }
    },
    {
      "method": "GET",
      "path": "/order/d7f3d034-de87-43e4-80ad-6945bebe0dd9/service",
      "status": 200,
      "durationMs": 169,
      "responseSummary": {
        "dataLength": 1
      }
    },
    {
      "method": "GET",
      "path": "/order/d7f57e0b-a830-4459-b7f7-a6d688719968/service",
      "status": 200,
      "durationMs": 172,
      "responseSummary": {
        "dataLength": 1
      }
    },
    {
      "method": "GET",
      "path": "/order/d7ff25da-dcb5-477c-b766-9854ccaa2968/service",
      "status": 200,
      "durationMs": 156,
      "responseSummary": {
        "dataLength": 1
      }
    },
    {
      "method": "GET",
      "path": "/order/d802f5b2-7625-4c9a-8e87-edd5be89b77a/service",
      "status": 200,
      "durationMs": 182,
      "responseSummary": {
        "dataLength": 1
      }
    },
    {
      "method": "GET",
      "path": "/order/d8084a8e-29bf-4af7-b455-5218ab667def/service",
      "status": 200,
      "durationMs": 184,
      "responseSummary": {
        "dataLength": 2
      }
    },
    {
      "method": "GET",
      "path": "/order/d808aeae-9554-48ba-8a12-82a5e70e4b40/service",
      "status": 200,
      "durationMs": 170,
      "responseSummary": {
        "dataLength": 2
      }
    },
    {
      "method": "GET",
      "path": "/order/d814a6d7-a14e-48e5-9952-3895792dd112/service",
      "status": 200,
      "durationMs": 173,
      "responseSummary": {
        "dataLength": 0
      }
    },
    {
      "method": "GET",
      "path": "/order/d8302cbc-5c22-4a27-839a-3ecef1db3d5a/service",
      "status": 200,
      "durationMs": 170,
      "responseSummary": {
        "dataLength": 1
      }
    },
    {
      "method": "GET",
      "path": "/order/d836e583-3f91-4e2b-a497-9744acc7a098/service",
      "status": 200,
      "durationMs": 159,
      "responseSummary": {
        "dataLength": 2
      }
    },
    {
      "method": "GET",
      "path": "/order/d838446b-4442-4540-af80-56eab6950790/service",
      "status": 200,
      "durationMs": 202,
      "responseSummary": {
        "dataLength": 1
      }
    },
    {
      "method": "GET",
      "path": "/order/d839921a-25e2-4062-9424-2ad3e0b92b56/service",
      "status": 200,
      "durationMs": 184,
      "responseSummary": {
        "dataLength": 0
      }
    },
    {
      "method": "GET",
      "path": "/order/d83ce393-e84d-4a35-9350-b358b2ffe0b6/service",
      "status": 200,
      "durationMs": 160,
      "responseSummary": {
        "dataLength": 1
      }
    },
    {
      "method": "GET",
      "path": "/order/d843e7e4-f9e1-42b5-944f-2ac31ed3cb05/service",
      "status": 200,
      "durationMs": 164,
      "responseSummary": {
        "dataLength": 0
      }
    },
    {
      "method": "GET",
      "path": "/order/d862b441-be66-494b-a6f9-f21c4142e80b/service",
      "status": 200,
      "durationMs": 168,
      "responseSummary": {
        "dataLength": 1
      }
    },
    {
      "method": "GET",
      "path": "/order/d86adf86-31e9-4a32-bf5e-e0e1433aab40/service",
      "status": 200,
      "durationMs": 175,
      "responseSummary": {
        "dataLength": 1
      }
    },
    {
      "method": "GET",
      "path": "/order/d8844dda-caab-4fd2-8e1f-c2990cc8bb09/service",
      "status": 200,
      "durationMs": 166,
      "responseSummary": {
        "dataLength": 1
      }
    },
    {
      "method": "GET",
      "path": "/order/d890f31b-fb46-40bf-b8c8-09821ea73d02/service",
      "status": 200,
      "durationMs": 179,
      "responseSummary": {
        "dataLength": 1
      }
    },
    {
      "method": "GET",
      "path": "/order/d898e8d3-a0a7-4ba6-8ec3-b224425bfbc7/service",
      "status": 200,
      "durationMs": 161,
      "responseSummary": {
        "dataLength": 1
      }
    },
    {
      "method": "GET",
      "path": "/order/d89cfea2-eeac-466c-978d-5fc7fcdcbdf2/service",
      "status": 200,
      "durationMs": 158,
      "responseSummary": {
        "dataLength": 0
      }
    },
    {
      "method": "GET",
      "path": "/order/d89e9f32-3696-4005-833b-714585888687/service",
      "status": 200,
      "durationMs": 158,
      "responseSummary": {
        "dataLength": 0
      }
    },
    {
      "method": "GET",
      "path": "/order/d8a3bbd8-9d1e-45d7-8192-7b068ded76de/service",
      "status": 200,
      "durationMs": 159,
      "responseSummary": {
        "dataLength": 1
      }
    },
    {
      "method": "GET",
      "path": "/order/d8a5ad5d-6ddb-4a33-9239-ab21e14f7c63/service",
      "status": 200,
      "durationMs": 201,
      "responseSummary": {
        "dataLength": 1
      }
    },
    {
      "method": "GET",
      "path": "/order/d8a81ee5-b15a-4096-bf60-92ccaa2efc9d/service",
      "status": 200,
      "durationMs": 156,
      "responseSummary": {
        "dataLength": 2
      }
    },
    {
      "method": "GET",
      "path": "/order/d8cfb09a-f6ac-4752-9642-d22ff00eb80d/service",
      "status": 200,
      "durationMs": 158,
      "responseSummary": {
        "dataLength": 1
      }
    },
    {
      "method": "GET",
      "path": "/order/d8d0bbd9-43f7-4283-9145-9f41f7a76682/service",
      "status": 200,
      "durationMs": 172,
      "responseSummary": {
        "dataLength": 4
      }
    },
    {
      "method": "GET",
      "path": "/order/d8d1c51e-4a94-4601-b7c1-d841a19f79fc/service",
      "status": 200,
      "durationMs": 174,
      "responseSummary": {
        "dataLength": 2
      }
    },
    {
      "method": "GET",
      "path": "/order/d8d2d9cf-74ad-4b8d-bdea-cd45b845920f/service",
      "status": 200,
      "durationMs": 175,
      "responseSummary": {
        "dataLength": 0
      }
    },
    {
      "method": "GET",
      "path": "/order/d90fd3b9-eabc-4fa3-ab9f-6c22c628b687/service",
      "status": 200,
      "durationMs": 184,
      "responseSummary": {
        "dataLength": 2
      }
    },
    {
      "method": "GET",
      "path": "/order/61294c10-23d3-48b8-89d6-e12641d7b18d/service",
      "status": 200,
      "durationMs": 199,
      "responseSummary": {
        "dataLength": 2
      }
    },
    {
      "method": "GET",
      "path": "/order/64f10bb7-80a8-4cbf-841d-2f3795b82635/service",
      "status": 200,
      "durationMs": 181,
      "responseSummary": {
        "dataLength": 0
      }
    },
    {
      "method": "GET",
      "path": "/order/ecda2948-5203-4073-8899-426a1250c26f/service",
      "status": 200,
      "durationMs": 186,
      "responseSummary": {
        "dataLength": 1
      }
    },
    {
      "method": "GET",
      "path": "/order/ecdee276-ff42-498f-be57-55a0ea2f9dd6/service",
      "status": 200,
      "durationMs": 194,
      "responseSummary": {
        "dataLength": 1
      }
    },
    {
      "method": "GET",
      "path": "/order/ecebac67-c1aa-4340-9b6b-f6d320c23faa/service",
      "status": 200,
      "durationMs": 204,
      "responseSummary": {
        "dataLength": 1
      }
    },
    {
      "method": "GET",
      "path": "/order/ecedecb5-abfe-4915-8dde-24ff21e2e682/service",
      "status": 200,
      "durationMs": 186,
      "responseSummary": {
        "dataLength": 1
      }
    },
    {
      "method": "GET",
      "path": "/order/ecf46ea6-e628-45a7-8d65-d260689d488c/service",
      "status": 200,
      "durationMs": 240,
      "responseSummary": {
        "dataLength": 1
      }
    },
    {
      "method": "GET",
      "path": "/order/ecfdd199-3dd6-4a2d-8498-c08056d3735a/service",
      "status": 200,
      "durationMs": 194,
      "responseSummary": {
        "dataLength": 3
      }
    },
    {
      "method": "GET",
      "path": "/order/ed034e0b-4f13-413e-a969-d41f11884845/service",
      "status": 200,
      "durationMs": 208,
      "responseSummary": {
        "dataLength": 1
      }
    },
    {
      "method": "GET",
      "path": "/order/ed0f4e27-4384-4b11-b3e4-1f1babf14006/service",
      "status": 200,
      "durationMs": 173,
      "responseSummary": {
        "dataLength": 0
      }
    },
    {
      "method": "GET",
      "path": "/order/ed1164ef-ebc3-481e-81a7-c793ddb9aaca/service",
      "status": 200,
      "durationMs": 169,
      "responseSummary": {
        "dataLength": 1
      }
    },
    {
      "method": "GET",
      "path": "/order/ed21fce1-8208-4e0f-b190-7fb2b67028e2/service",
      "status": 200,
      "durationMs": 171,
      "responseSummary": {
        "dataLength": 0
      }
    },
    {
      "method": "GET",
      "path": "/order/ed393fce-abb0-4771-8dc9-129ae637c0c7/service",
      "status": 200,
      "durationMs": 168,
      "responseSummary": {
        "dataLength": 1
      }
    },
    {
      "method": "GET",
      "path": "/order/ed528dfa-b22b-47cc-a3f1-1321118a8974/service",
      "status": 200,
      "durationMs": 174,
      "responseSummary": {
        "dataLength": 1
      }
    }
  ],
  "capturedAt": "2026-04-27T20:59:39.524Z"
}